eyja_aws/__init__.py
eyja_aws/aws_hub.py
eyja_aws_hub-0.1.1.dist-info/METADATA
eyja_aws_hub-0.1.1.dist-info/WHEEL
eyja_aws_hub-0.1.1.dist-info/top_level.txt
eyja_aws_hub-0.1.1.dist-info/zip-safe
eyja_aws_hub-0.1.1.dist-info/RECORD
